sdplc/__init__.py
sdplc/modbus/__init__.py
sdplc/modbus/client.py
sdplc/modbus/schemas.py
sdplc/modbus/server.py
sdplc/opcua/Opc.Ua.NodeSet2.xml
sdplc/opcua/__init__.py
sdplc/opcua/client.py
sdplc/opcua/schemas.py
sdplc/opcua/server.py
sdplc/router.py
sdplc/schemas.py
sdplc/sdplc.py
sdplc-1.0.7.dist-info/LICENSE
sdplc-1.0.7.dist-info/METADATA
sdplc-1.0.7.dist-info/WHEEL
sdplc-1.0.7.dist-info/RECORD
