Metadata-Version: 2.1
Name: sdplc
Version: 1.0.7
Summary: PLC Simulation and Remote Control
Home-page: https://github.com/ulfaric/SDPLC
License: CC-BY-NC-ND-4.0
Author: ulfaric
Author-email: ryf0510@live.com
Requires-Python: >=3.10,<4.0
Classifier: License :: Other/Proprietary License
Classifier: Programming Language :: Python :: 3
Classifier: Programming Language :: Python :: 3.10
Classifier: Programming Language :: Python :: 3.11
Classifier: Programming Language :: Python :: 3.12
Requires-Dist: akatosh (>=3.1.7,<4.0.0)
Requires-Dist: asyncua (>=1.1.0,<2.0.0)
Requires-Dist: colorlog (>=6.8.2,<7.0.0)
Requires-Dist: fasterapi (>=0.0.46,<0.0.47)
Requires-Dist: numpy (>=1.26.4,<2.0.0)
Requires-Dist: pymodbus (>=3.6.8,<4.0.0)
Requires-Dist: pyyaml (>=6.0.1,<7.0.0)
Project-URL: Repository, https://github.com/ulfaric/SDPLC
